sharepoint_rest_api/__init__.py
sharepoint_rest_api/api_client.py
sharepoint_rest_api/configuration.py
sharepoint_rest_api/rest.py
sharepoint_rest_api/api/__init__.py
sharepoint_rest_api/api/lists_api.py
sharepoint_rest_api/api/sites_api.py
sharepoint_rest_api/api/webs_api.py
sharepoint_rest_api/models/__init__.py
sharepoint_rest_api/models/sp_odata_result.py
test/__init__.py
test/test_lists_api.py
test/test_sites_api.py
test/test_sp_odata_result.py
test/test_webs_api.py
sharepoint_rest_api_client-1.0.0.dist-info/METADATA
sharepoint_rest_api_client-1.0.0.dist-info/WHEEL
sharepoint_rest_api_client-1.0.0.dist-info/top_level.txt
sharepoint_rest_api_client-1.0.0.dist-info/RECORD
