Metadata-Version: 2.1
Name: sharepoint-rest-api-client
Version: 1.0.0
Summary: Sharepoint REST V1 Client
Home-page: 
Author-email: 
Keywords: Swagger,Sharepoint REST V1 Client
Requires-Dist: urllib3 (>=1.15)
Requires-Dist: six (>=1.10)
Requires-Dist: certifi
Requires-Dist: python-dateutil
